texla/Reporter.py
texla/__init__.py
texla/i18n.yaml
texla/log.py
texla/Exceptions/TexlaExceptions.py
texla/Exceptions/__init__.py
texla/PageTree/Babel.py
texla/PageTree/Exporter.py
texla/PageTree/Page.py
texla/PageTree/PageTree.py
texla/PageTree/TheoremsManager.py
texla/PageTree/__init__.py
texla/Parser/Parser.py
texla/Parser/PreParser.py
texla/Parser/TreeExplorer.py
texla/Parser/__init__.py
texla/Parser/Blocks/AbstractBlock.py
texla/Parser/Blocks/AlignmentBlocks.py
texla/Parser/Blocks/Block.py
texla/Parser/Blocks/BreakBlocks.py
texla/Parser/Blocks/ClearBlocks.py
texla/Parser/Blocks/CodeBlocks.py
texla/Parser/Blocks/CommandsGroupBlock.py
texla/Parser/Blocks/DefaultBlock.py
texla/Parser/Blocks/DocumentBlock.py
texla/Parser/Blocks/DotBlock.py
texla/Parser/Blocks/FigureBlocks.py
texla/Parser/Blocks/FormattingBlocks.py
texla/Parser/Blocks/HeaderBlock.py
texla/Parser/Blocks/ListBlocks.py
texla/Parser/Blocks/MathBlocks.py
texla/Parser/Blocks/NoOptCommandBlock.py
texla/Parser/Blocks/NoteBlocks.py
texla/Parser/Blocks/ReferenceBlocks.py
texla/Parser/Blocks/SectionBlock.py
texla/Parser/Blocks/SpaceBlock.py
texla/Parser/Blocks/TabularBlocks.py
texla/Parser/Blocks/TextBlocks.py
texla/Parser/Blocks/TheoremBlocks.py
texla/Parser/Blocks/VerbatimBlock.py
texla/Parser/Blocks/__init__.py
texla/Parser/Blocks/Utilities/CommandParser.py
texla/Parser/Blocks/Utilities/EnvironmentParser.py
texla/Parser/Blocks/Utilities/MacroParser.py
texla/Parser/Blocks/Utilities/__init__.py
texla/Parser/Blocks/Utilities/utility.py
texla/Parser/Utilities/CommandParser.py
texla/Parser/Utilities/EnvironmentParser.py
texla/Parser/Utilities/MacroParser.py
texla/Parser/Utilities/__init__.py
texla/Parser/Utilities/utility.py
texla/Renderers/MediaWikiRenderer.py
texla/Renderers/Renderer.py
texla/Renderers/__init__.py
texla/Renderers/utils.py
texla/Renderers/plugins/MathCheck.py
texla/Renderers/plugins/__init__.py
texla-0.1.2.dist-info/DESCRIPTION.rst
texla-0.1.2.dist-info/METADATA
texla-0.1.2.dist-info/RECORD
texla-0.1.2.dist-info/WHEEL
texla-0.1.2.dist-info/entry_points.txt
texla-0.1.2.dist-info/metadata.json
texla-0.1.2.dist-info/top_level.txt
