Metadata-Version: 2.0
Name: texla
Version: 0.1.2
Summary: UNKNOWN
Home-page: https://github.com/WikiToLearn/texla
Author: Davide Valsecchi
Author-email: valsecchi.davide94@gmail.com
License: GPL
Platform: UNKNOWN
Requires-Python: >=3
Requires-Dist: PyYaml
Requires-Dist: requests
